turingmark/__init__.py
turingmark/module.py
turingmark-0.1.0.dist-info/METADATA
turingmark-0.1.0.dist-info/WHEEL
turingmark-0.1.0.dist-info/RECORD
